authentication/__init__.py
authentication/authentication.py
etrade/__init__.py
etrade/etrade.py
execute/__init__.py
execute/execute.py
model/__init__.py
model/investor_views.py
model/model.py
strategies/__init__.py
strategies/example_strategy.py
strategies/strategy.py
tests/__init__.py
tests/test_api.py
tests/test_authentication.py
tests/test_etrade.py
tests/test_execute.py
tests/test_model.py
tests/test_utils.py
utils/__init__.py
utils/credentials.py
utils/fake_data.py
utils/list_accounts.py
utils/logging_config.py
utils/mock_data.py
utils/mock_responses.py
utils/portfolio.py
utils/vif.py
etradebot-3.0.5.dist-info/LICENSE
etradebot-3.0.5.dist-info/METADATA
etradebot-3.0.5.dist-info/WHEEL
etradebot-3.0.5.dist-info/dependency_links.txt
etradebot-3.0.5.dist-info/top_level.txt
etradebot-3.0.5.dist-info/RECORD
