Metadata-Version: 2.1
Name: etradebot
Version: 3.0.5
Summary: A Python-based trading bot for the E-Trade platform
Home-page: https://github.com/nathanramoscfa/etradebot
Author: Nathan Ramos, CFA®
Author-email: nathan.ramos.github@gmail.com
License: MIT
Classifier: Development Status :: 3 - Alpha
Classifier: Intended Audience :: Developers
Classifier: License :: OSI Approved :: MIT License
Classifier: Programming Language :: Python :: 3.11
Requires-Python: >=3.11, <3.12
License-File: LICENSE
Requires-Dist: cvxpy ==1.3.0
Requires-Dist: dicttoxml ==1.7.16
Requires-Dist: jupyterlab ==3.6.1
Requires-Dist: keyring ==23.13.1
Requires-Dist: matplotlib ==3.7.1
Requires-Dist: numpy ==1.24.2
Requires-Dist: pandas >=2.0.3
Requires-Dist: pyportfolioopt ==1.5.5
Requires-Dist: pytz ==2022.7.1
Requires-Dist: recommonmark
Requires-Dist: requests ==2.31.0
Requires-Dist: scikit-learn ==1.2.2
Requires-Dist: scipy ==1.10.1
Requires-Dist: selenium ==4.8.2
Requires-Dist: setuptools <=64.0.2
Requires-Dist: sphinx ==6.1.3
Requires-Dist: sphinx-rtd-theme
Requires-Dist: statsmodels ==0.13.5
Requires-Dist: tqdm ==4.65.0
Requires-Dist: xmltodict ==0.13.0
Requires-Dist: yahooquery ==2.3.6
Requires-Dist: yfinance ==0.2.12
Provides-Extra: bloomberg
Requires-Dist: blpapi ==3.19.1 ; extra == 'bloomberg'
Requires-Dist: tia ; extra == 'bloomberg'
Provides-Extra: github_forks
Requires-Dist: pyetrade ==1.4.1 ; extra == 'github_forks'
Requires-Dist: pandas-market-calendars ==4.3.3 ; extra == 'github_forks'
